djangoldp_becknld/__init__.py
djangoldp_becknld/admin.py
djangoldp_becknld/apps.py
djangoldp_becknld/consts.py
djangoldp_becknld/djangoldp_urls.py
djangoldp_becknld/activities/__init__.py
djangoldp_becknld/activities/verbs.py
djangoldp_becknld/migrations/0001_initial.py
djangoldp_becknld/migrations/__init__.py
djangoldp_becknld/models/__base.py
djangoldp_becknld/models/__init__.py
djangoldp_becknld/models/delivery_option.py
djangoldp_becknld/models/item.py
djangoldp_becknld/models/payment_option.py
djangoldp_becknld/models/transaction.py
djangoldp_becknld/models/zzz_signals.py
djangoldp_becknld/models/offer/__init__.py
djangoldp_becknld/models/offer/address.py
djangoldp_becknld/models/offer/delivery_method.py
djangoldp_becknld/models/offer/invoice.py
djangoldp_becknld/models/offer/offer.py
djangoldp_becknld/models/offer/price_component.py
djangoldp_becknld/models/offer/price_specification.py
djangoldp_becknld/models/order/__init__.py
djangoldp_becknld/models/order/order.py
djangoldp_becknld/models/order/order_item.py
djangoldp_becknld/models/order/quantitative_value.py
djangoldp_becknld/tests/README.md
djangoldp_becknld/tests/__init__.py
djangoldp_becknld/tests/runner.py
djangoldp_becknld/tests/test_activities.py
djangoldp_becknld/tests/test_consts.py
djangoldp_becknld/tests/test_models.py
djangoldp_becknld/tests/test_utils.py
djangoldp_becknld/tests/test_views.py
djangoldp_becknld/views/__init__.py
djangoldp_becknld/views/transaction/__base_viewset.py
djangoldp_becknld/views/transaction/__init__.py
djangoldp_becknld/views/transaction/inbox_activity_viewset.py
djangoldp_becknld/views/transaction/inbox_viewset.py
djangoldp_becknld/views/transaction/outbox_viewset.py
djangoldp_becknld/views/transaction/inbox/__init__.py
djangoldp_becknld/views/transaction/inbox/confirm.py
djangoldp_becknld/views/transaction/inbox/init.py
djangoldp_becknld/views/transaction/inbox/on_confirm.py
djangoldp_becknld/views/transaction/inbox/on_init.py
djangoldp_becknld-2.0.0.dist-info/METADATA
djangoldp_becknld-2.0.0.dist-info/WHEEL
djangoldp_becknld-2.0.0.dist-info/top_level.txt
djangoldp_becknld-2.0.0.dist-info/RECORD
