Metadata-Version: 2.1
Name: djangoldp-becknld
Version: 2.0.0
Summary: djangoldp package for Beckn-LD Draft
Home-page: https://git.startinblox.com/djangoldp-packages/djangoldp-becknld
Author: Startinblox
Author-email: jbaptiste@startinblox.com
License: MIT
Classifier: Programming Language :: Python :: 3
Requires-Dist: djangoldp~=4.0.0
Requires-Dist: djangoldp-account~=4.0.0
Provides-Extra: include_package_data
Requires-Dist: True; extra == "include-package-data"
